setup.py
Django_stackoverflow.egg-info/PKG-INFO
Django_stackoverflow.egg-info/SOURCES.txt
Django_stackoverflow.egg-info/dependency_links.txt
Django_stackoverflow.egg-info/requires.txt
Django_stackoverflow.egg-info/top_level.txt
Stackoverflow/StackoverflowMiddleWare.py
Stackoverflow/__init__.py