Metadata-Version: 1.0
Name: Django-stackoverflow
Version: 0.1.7
Summary: Useful Django exception query with stackoverflow site
Home-page: https://pypi.python.org/pypi?name=Stackoverflow&version=0.1.3&:action=display
Author: FizLin
Author-email: 18818261892@163.com
License: UNKNOWN
Platform: UNKNOWN
